{
  "type": "ars_nouveau:enchanting_apparatus",
  "keepNbtOfReagent": true,
  "output": {
    "item": "minecraft:enchanted_book",
		"nbt": {
			"StoredEnchantments": [
				{
					"id": "combatroll:longfooted",
					"lvl": 4
				}
			]
		}
	},
  "pedestalItems": [
    {
      "item": "minecraft:ender_pearl"
    },
    {
      "item": "minecraft:slime_ball"
    },
    {
      "item": "minecraft:clay_ball"
    },
    {
      "item": "minecraft:snowball"
    },
    {
      "item": "culturaldelights:rice_ball"
	},
    {
      "item": "minecraft:diamond"
    }
  ],
  "reagent": [
    {
      "item": "minecraft:book"
    }
  ],
  "sourceCost": 5000
}